rwt/__init__.py
rwt/__main__.py
rwt/commands.py
rwt/deps.py
rwt/launch.py
rwt/read-deps.py
rwt/scripts.py
rwt/tests/test_deps.py
rwt/tests/test_launch.py
rwt/tests/test_scripts.py
rwt-4.4.3.dist-info/LICENSE
rwt-4.4.3.dist-info/METADATA
rwt-4.4.3.dist-info/WHEEL
rwt-4.4.3.dist-info/entry_points.txt
rwt-4.4.3.dist-info/top_level.txt
rwt-4.4.3.dist-info/RECORD
